ipytextual/__init__.py
ipytextual/driver.py
ipytextual/widget.py
ipytextual/static/index.js
ipytextual-0.1.1.dist-info/METADATA
ipytextual-0.1.1.dist-info/WHEEL
ipytextual-0.1.1.dist-info/licenses/LICENSE.txt
ipytextual-0.1.1.dist-info/RECORD
