Metadata-Version: 2.1
Name: ipytextual
Version: 0.1.1
Summary: Jupyter Textual-based Widget
Project-URL: Homepage, https://github.com/davidbrochart/ipytextual
Author-email: David Brochart <david.brochart@gmail.com>
License: Copyright (c) 2023 David Brochart
License-File: LICENSE.txt
Keywords: IPython,Jupyter,Widgets
Classifier: Framework :: Jupyter
Classifier: Intended Audience :: Developers
Classifier: Intended Audience :: Science/Research
Classifier: License :: OSI Approved :: BSD License
Classifier: Programming Language :: Python
Classifier: Programming Language :: Python :: 3
Classifier: Programming Language :: Python :: 3.7
Classifier: Programming Language :: Python :: 3.8
Classifier: Programming Language :: Python :: 3.9
Classifier: Programming Language :: Python :: 3.10
Classifier: Programming Language :: Python :: 3.11
Requires-Python: >=3.7
Requires-Dist: anywidget<1,>=0.6.3
Requires-Dist: textual
